Workbook

Sheet Summary
A1: Autobiz Financial Model | B1: Autobiz Financial Model | C1: Autobiz Financial Model | D1: Autobiz Financial Model | E1: Autobiz Financial Model | F1: Autobiz Financial Model | G1: Autobiz Financial Model | H1: Autobiz Financial Model | I1: Autobiz Financial Model | J1: Autobiz Financial Model | K1: Autobiz Financial Model | L1: Autobiz Financial Model | M1: Autobiz Financial Model
A2: Illustrative 12-month planning model — inputs are hypotheses, not market evidence | B2: Illustrative 12-month planning model — inputs are hypotheses, not market evidence | C2: Illustrative 12-month planning model — inputs are hypotheses, not market evidence | D2: Illustrative 12-month planning model — inputs are hypotheses, not market evidence | E2: Illustrative 12-month planning model — inputs are hypotheses, not market evidence | F2: Illustrative 12-month planning model — inputs are hypotheses, not market evidence | G2: Illustrative 12-month planning model — inputs are hypotheses, not market evidence | H2: Illustrative 12-month planning model — inputs are hypotheses, not market evidence | I2: Illustrative 12-month planning model — inputs are hypotheses, not market evidence | J2: Illustrative 12-month planning model — inputs are hypotheses, not market evidence | K2: Illustrative 12-month planning model — inputs are hypotheses, not market evidence | L2: Illustrative 12-month planning model — inputs are hypotheses, not market evidence | M2: Illustrative 12-month planning model — inputs are hypotheses, not market evidence
A4: Planning scenario | B4: Base
A5: Year 1 revenue | B5: =SUM(Forecast!B9:M9) -> 70500
A6: Year 1 contribution | B6: =SUM(Forecast!B18:M18) -> 54735
A7: Contribution margin | B7: =IFERROR(B6/B5,0) -> 0.77638298
A8: Ending cash | B8: =Forecast!M24 -> 52735
A9: Break-even month | B9: =IFERROR(INDEX(Forecast!B3:M3,1,MATCH(TRUE,Forecast!B21:M21>=0,0)),"Not in year 1") -> Not in year 1
A11: Month | B11: Revenue | C11: Contribution | D11: Closing cash
A12: M1 | B12: =Forecast!B9 -> 1750 | C12: =Forecast!B18 -> 1522.5 | D12: =Forecast!B24 -> 10522.5
A13: M2 | B13: =Forecast!C9 -> 2500 | C13: =Forecast!C18 -> 2075 | D13: =Forecast!C24 -> 11597.5
A14: M3 | B14: =Forecast!D9 -> 3250 | C14: =Forecast!D18 -> 2627.5 | D14: =Forecast!D24 -> 13225
A15: M4 | B15: =Forecast!E9 -> 4000 | C15: =Forecast!E18 -> 3180 | D15: =Forecast!E24 -> 15405
A16: M5 | B16: =Forecast!F9 -> 4750 | C16: =Forecast!F18 -> 3732.5 | D16: =Forecast!F24 -> 18137.5
A17: M6 | B17: =Forecast!G9 -> 5500 | C17: =Forecast!G18 -> 4285 | D17: =Forecast!G24 -> 21422.5
A18: M7 | B18: =Forecast!H9 -> 6250 | C18: =Forecast!H18 -> 4837.5 | D18: =Forecast!H24 -> 25260
A19: M8 | B19: =Forecast!I9 -> 7000 | C19: =Forecast!I18 -> 5390 | D19: =Forecast!I24 -> 29650
A20: M9 | B20: =Forecast!J9 -> 7750 | C20: =Forecast!J18 -> 5942.5 | D20: =Forecast!J24 -> 34592.5
A21: M10 | B21: =Forecast!K9 -> 8500 | C21: =Forecast!K18 -> 6495 | D21: =Forecast!K24 -> 40087.5
A22: M11 | B22: =Forecast!L9 -> 9250 | C22: =Forecast!L18 -> 7047.5 | D22: =Forecast!L24 -> 46135
A23: M12 | B23: =Forecast!M9 -> 10000 | C23: =Forecast!M18 -> 7600 | D23: =Forecast!M24 -> 52735

Sheet Assumptions
A1: Assumptions | B1: Assumptions | C1: Assumptions | D1: Assumptions | E1: Assumptions | F1: Assumptions
A2: Blue text on gold cells indicates editable hypotheses | B2: Blue text on gold cells indicates editable hypotheses | C2: Blue text on gold cells indicates editable hypotheses | D2: Blue text on gold cells indicates editable hypotheses | E2: Blue text on gold cells indicates editable hypotheses | F2: Blue text on gold cells indicates editable hypotheses
A4: Driver | B4: Base | C4: Conservative | D4: Upside | E4: Unit | F4: Basis / note
A5: Starting customers | B5: 0 | C5: 0 | D5: 0 | E5: customers | F5: Pre-revenue starting point
A6: New customers in month 1 | B6: 1 | C6: 0 | D6: 2 | E6: customers | F6: Hypothesis to validate
A7: Monthly new-customer growth | B7: 0.15 | C7: 0.05 | D7: 0.25 | E7: % | F7: Hypothesis to validate
A8: Monthly customer churn | B8: 0.03 | C8: 0.06 | D8: 0.02 | E8: % | F8: Hypothesis to validate
A9: Monthly subscription price | B9: 750 | C9: 500 | D9: 1000 | E9: EUR/customer | F9: Hypothesis to test through paid offers
A10: One-time setup fee | B10: 1000 | C10: 500 | D10: 1500 | E10: EUR/new customer | F10: Hypothesis to test through paid offers
A11: Variable delivery hours/customer | B11: 3 | C11: 5 | D11: 2 | E11: hours/month | F11: Includes operator time
A12: Loaded hourly delivery cost | B12: 50 | C12: 50 | D12: 50 | E12: EUR/hour | F12: Opportunity cost or contractor rate
A13: AI/API cost/customer | B13: 25 | C13: 40 | D13: 20 | E13: EUR/month | F13: Placeholder until measured
A14: Payment and variable fees | B14: 0.03 | C14: 0.035 | D14: 0.025 | E14: % revenue | F14: Illustrative blended variable fee
A15: Fixed software and hosting | B15: 250 | C15: 300 | D15: 300 | E15: EUR/month | F15: Placeholder until vendors selected
A16: Sales and marketing | B16: 500 | C16: 300 | D16: 1000 | E16: EUR/month | F16: Founder-led initially
... A18: Opening cash | B18: 10000 | C18: 10000 | D18: 10000 | E18: EUR | F18: Planning input
A20: Instructions | B20: Instructions | C20: Instructions | D20: Instructions | E20: Instructions | F20: Instructions
A21: 1 | B21: Replace hypotheses with interview and pilot evidence.
A22: 2 | B22: Keep founder/operator time in variable cost; do not treat it as free.
A23: 3 | B23: The forecast currently uses the Base column. Scenarios are comparison inputs.

Sheet Forecast
A1: 12-Month Forecast | B1: 12-Month Forecast | C1: 12-Month Forecast | D1: 12-Month Forecast | E1: 12-Month Forecast | F1: 12-Month Forecast | G1: 12-Month Forecast | H1: 12-Month Forecast | I1: 12-Month Forecast | J1: 12-Month Forecast | K1: 12-Month Forecast | L1: 12-Month Forecast | M1: 12-Month Forecast
A2: Formula-driven from Base assumptions | B2: Formula-driven from Base assumptions | C2: Formula-driven from Base assumptions | D2: Formula-driven from Base assumptions | E2: Formula-driven from Base assumptions | F2: Formula-driven from Base assumptions | G2: Formula-driven from Base assumptions | H2: Formula-driven from Base assumptions | I2: Formula-driven from Base assumptions | J2: Formula-driven from Base assumptions | K2: Formula-driven from Base assumptions | L2: Formula-driven from Base assumptions | M2: Formula-driven from Base assumptions
A3: Metric | B3: M1 | C3: M2 | D3: M3 | E3: M4 | F3: M5 | G3: M6 | H3: M7 | I3: M8 | J3: M9 | K3: M10 | L3: M11 | M3: M12
A4: Opening customers | B4: =Assumptions!B5 -> 0 | C4: =B7 -> 1 | D4: =C7 -> 2 | E4: =D7 -> 3 | F4: =E7 -> 4 | G4: =F7 -> 5 | H4: =G7 -> 6 | I4: =H7 -> 7 | J4: =I7 -> 8 | ... M4: =L7 -> 11
A5: New customers | B5: =Assumptions!B6 -> 1 | C5: =MAX(0,ROUND(B5*(1+Assumptions!$B$7),0)) -> 1 | D5: =MAX(0,ROUND(C5*(1+Assumptions!$B$7),0)) -> 1 | E5: =MAX(0,ROUND(D5*(1+Assumptions!$B$7),0)) -> 1 | F5: =MAX(0,ROUND(E5*(1+Assumptions!$B$7),0)) -> 1 | G5: =MAX(0,ROUND(F5*(1+Assumptions!$B$7),0)) -> 1 | H5: =MAX(0,ROUND(G5*(1+Assumptions!$B$7),0)) -> 1 | I5: =MAX(0,ROUND(H5*(1+Assumptions!$B$7),0)) -> 1 | J5: =MAX(0,ROUND(I5*(1+Assumptions!$B$7),0)) -> 1 | ... M5: =MAX(0,ROUND(L5*(1+Assumptions!$B$7),0)) -> 1
A6: Churned customers | B6: =MIN(B4,ROUND(B4*Assumptions!$B$8,0)) -> 0 | C6: =MIN(C4,ROUND(C4*Assumptions!$B$8,0)) -> 0 | D6: =MIN(D4,ROUND(D4*Assumptions!$B$8,0)) -> 0 | E6: =MIN(E4,ROUND(E4*Assumptions!$B$8,0)) -> 0 | F6: =MIN(F4,ROUND(F4*Assumptions!$B$8,0)) -> 0 | G6: =MIN(G4,ROUND(G4*Assumptions!$B$8,0)) -> 0 | H6: =MIN(H4,ROUND(H4*Assumptions!$B$8,0)) -> 0 | I6: =MIN(I4,ROUND(I4*Assumptions!$B$8,0)) -> 0 | ... M6: =MIN(M4,ROUND(M4*Assumptions!$B$8,0)) -> 0
A7: Closing customers | B7: =B4+B5-B6 -> 1 | C7: =C4+C5-C6 -> 2 | D7: =D4+D5-D6 -> 3 | E7: =E4+E5-E6 -> 4 | F7: =F4+F5-F6 -> 5 | G7: =G4+G5-G6 -> 6 | H7: =H4+H5-H6 -> 7 | I7: =I4+I5-I6 -> 8 | ... M7: =M4+M5-M6 -> 12
A9: Revenue | B9: =SUM(B10:B11) -> 1750 | C9: =SUM(C10:C11) -> 2500 | D9: =SUM(D10:D11) -> 3250 | E9: =SUM(E10:E11) -> 4000 | F9: =SUM(F10:F11) -> 4750 | G9: =SUM(G10:G11) -> 5500 | H9: =SUM(H10:H11) -> 6250 | I9: =SUM(I10:I11) -> 7000 | ... M9: =SUM(M10:M11) -> 10000
A10: Subscription revenue | B10: =B7*Assumptions!$B$9 -> 750 | C10: =C7*Assumptions!$B$9 -> 1500 | D10: =D7*Assumptions!$B$9 -> 2250 | E10: =E7*Assumptions!$B$9 -> 3000 | F10: =F7*Assumptions!$B$9 -> 3750 | G10: =G7*Assumptions!$B$9 -> 4500 | H10: =H7*Assumptions!$B$9 -> 5250 | I10: =I7*Assumptions!$B$9 -> 6000 | ... M10: =M7*Assumptions!$B$9 -> 9000
A11: Setup revenue | B11: =B5*Assumptions!$B$10 -> 1000 | C11: =C5*Assumptions!$B$10 -> 1000 | D11: =D5*Assumptions!$B$10 -> 1000 | E11: =E5*Assumptions!$B$10 -> 1000 | F11: =F5*Assumptions!$B$10 -> 1000 | G11: =G5*Assumptions!$B$10 -> 1000 | H11: =H5*Assumptions!$B$10 -> 1000 | I11: =I5*Assumptions!$B$10 -> 1000 | ... M11: =M5*Assumptions!$B$10 -> 1000
A13: Variable costs | B13: =SUM(B14:B16) -> 227.5 | C13: =SUM(C14:C16) -> 425 | D13: =SUM(D14:D16) -> 622.5 | E13: =SUM(E14:E16) -> 820 | F13: =SUM(F14:F16) -> 1017.5 | G13: =SUM(G14:G16) -> 1215 | H13: =SUM(H14:H16) -> 1412.5 | I13: =SUM(I14:I16) -> 1610 | ... M13: =SUM(M14:M16) -> 2400
A14: Delivery labor | B14: =B7*Assumptions!$B$11*Assumptions!$B$12 -> 150 | C14: =C7*Assumptions!$B$11*Assumptions!$B$12 -> 300 | D14: =D7*Assumptions!$B$11*Assumptions!$B$12 -> 450 | E14: =E7*Assumptions!$B$11*Assumptions!$B$12 -> 600 | F14: =F7*Assumptions!$B$11*Assumptions!$B$12 -> 750 | G14: =G7*Assumptions!$B$11*Assumptions!$B$12 -> 900 | H14: =H7*Assumptions!$B$11*Assumptions!$B$12 -> 1050 | I14: =I7*Assumptions!$B$11*Assumptions!$B$12 -> 1200 | ... M14: =M7*Assumptions!$B$11*Assumptions!$B$12 -> 1800
A15: AI/API usage | B15: =B7*Assumptions!$B$13 -> 25 | C15: =C7*Assumptions!$B$13 -> 50 | D15: =D7*Assumptions!$B$13 -> 75 | E15: =E7*Assumptions!$B$13 -> 100 | F15: =F7*Assumptions!$B$13 -> 125 | G15: =G7*Assumptions!$B$13 -> 150 | H15: =H7*Assumptions!$B$13 -> 175 | I15: =I7*Assumptions!$B$13 -> 200 | ... M15: =M7*Assumptions!$B$13 -> 300
A16: Payment/variable fees | B16: =B9*Assumptions!$B$14 -> 52.5 | C16: =C9*Assumptions!$B$14 -> 75 | D16: =D9*Assumptions!$B$14 -> 97.5 | E16: =E9*Assumptions!$B$14 -> 120 | F16: =F9*Assumptions!$B$14 -> 142.5 | G16: =G9*Assumptions!$B$14 -> 165 | H16: =H9*Assumptions!$B$14 -> 187.5 | I16: =I9*Assumptions!$B$14 -> 210 | ... M16: =M9*Assumptions!$B$14 -> 300
A18: Contribution | B18: =B9-B13 -> 1522.5 | C18: =C9-C13 -> 2075 | D18: =D9-D13 -> 2627.5 | E18: =E9-E13 -> 3180 | F18: =F9-F13 -> 3732.5 | G18: =G9-G13 -> 4285 | H18: =H9-H13 -> 4837.5 | I18: =I9-I13 -> 5390 | ... M18: =M9-M13 -> 7600
A19: Contribution margin | B19: =IFERROR(B18/B9,0) -> 0.87 | C19: =IFERROR(C18/C9,0) -> 0.83 | D19: =IFERROR(D18/D9,0) -> 0.80846154 | E19: =IFERROR(E18/E9,0) -> 0.795 | F19: =IFERROR(F18/F9,0) -> 0.78578947 | G19: =IFERROR(G18/G9,0) -> 0.77909091 | H19: =IFERROR(H18/H9,0) -> 0.774 | I19: =IFERROR(I18/I9,0) -> 0.77 | ... M19: =IFERROR(M18/M9,0) -> 0.76
A20: Fixed operating costs | B20: =SUM(Assumptions!$B$15:$B$17) -> 1000 | C20: =SUM(Assumptions!$B$15:$B$17) -> 1000 | D20: =SUM(Assumptions!$B$15:$B$17) -> 1000 | E20: =SUM(Assumptions!$B$15:$B$17) -> 1000 | F20: =SUM(Assumptions!$B$15:$B$17) -> 1000 | G20: =SUM(Assumptions!$B$15:$B$17) -> 1000 | H20: =SUM(Assumptions!$B$15:$B$17) -> 1000 | I20: =SUM(Assumptions!$B$15:$B$17) -> 1000 | ... M20: =SUM(Assumptions!$B$15:$B$17) -> 1000
A21: Operating cash flow | B21: =B18-B20 -> 522.5 | C21: =C18-C20 -> 1075 | D21: =D18-D20 -> 1627.5 | E21: =E18-E20 -> 2180 | F21: =F18-F20 -> 2732.5 | G21: =G18-G20 -> 3285 | H21: =H18-H20 -> 3837.5 | I21: =I18-I20 -> 4390 | ... M21: =M18-M20 -> 6600
A23: Opening cash | B23: =Assumptions!$B$18 -> 10000 | C23: =B24 -> 10522.5 | D23: =C24 -> 11597.5 | E23: =D24 -> 13225 | F23: =E24 -> 15405 | G23: =F24 -> 18137.5 | H23: =G24 -> 21422.5 | I23: =H24 -> 25260 | J23: =I24 -> 29650 | ... M23: =L24 -> 46135
A24: Closing cash | B24: =B23+B21 -> 10522.5 | C24: =C23+C21 -> 11597.5 | D24: =D23+D21 -> 13225 | E24: =E23+E21 -> 15405 | F24: =F23+F21 -> 18137.5 | G24: =G23+G21 -> 21422.5 | H24: =H23+H21 -> 25260 | I24: =I23+I21 -> 29650 | ... M24: =M23+M21 -> 52735

Sheet Checks
A1: Model Checks | B1: Model Checks | C1: Model Checks | D1: Model Checks | E1: Model Checks | F1: Model Checks | G1: Model Checks
A2: PASS means formulas reconcile; assumptions remain unvalidated | B2: PASS means formulas reconcile; assumptions remain unvalidated | C2: PASS means formulas reconcile; assumptions remain unvalidated | D2: PASS means formulas reconcile; assumptions remain unvalidated | E2: PASS means formulas reconcile; assumptions remain unvalidated | F2: PASS means formulas reconcile; assumptions remain unvalidated | G2: PASS means formulas reconcile; assumptions remain unvalidated
A4: Check | B4: Actual | C4: Expected | D4: Difference | E4: Tolerance | F4: Status | G4: Where to fix / note
A5: Revenue equals components | B5: =SUM(Forecast!B9:M9)-SUM(Forecast!B10:M10)-SUM(Forecast!B11:M11) -> 0 | C5: 0 | D5: =B5-C5 -> 0 | E5: 0.01 | F5: =IF(ABS(D5)<=E5,"PASS","FAIL") -> PASS | G5: Forecast rows 9–11
A6: Variable costs equal components | B6: =SUM(Forecast!B13:M13)-SUM(Forecast!B14:M14)-SUM(Forecast!B15:M15)-SUM(Forecast!B16:M16) -> 0 | C6: 0 | D6: =B6-C6 -> 0 | E6: 0.01 | F6: =IF(ABS(D6)<=E6,"PASS","FAIL") -> PASS | G6: Forecast rows 13–16
A7: Customer roll-forward | B7: =SUM(Forecast!B7:M7)-SUM(Forecast!B4:M4)-SUM(Forecast!B5:M5)+SUM(Forecast!B6:M6) -> 0 | C7: 0 | D7: =B7-C7 -> 0 | E7: 0.01 | F7: =IF(ABS(D7)<=E7,"PASS","FAIL") -> PASS | G7: Forecast rows 4–7
A8: Cash roll-forward | B8: =SUM(Forecast!B24:M24)-SUM(Forecast!B23:M23)-SUM(Forecast!B21:M21) -> 0 | C8: 0 | D8: =B8-C8 -> 0 | E8: 0.01 | F8: =IF(ABS(D8)<=E8,"PASS","FAIL") -> PASS | G8: Forecast rows 21–24
A9: All required base assumptions populated | B9: =COUNT(Assumptions!B5:B18) -> 14 | C9: 14 | D9: =B9-C9 -> 0 | E9: 0 | F9: =IF(ABS(D9)<=E9,"PASS","FAIL") -> PASS | G9: Assumptions B5:B18
A11: MODEL STATUS | B11: =IF(COUNTIF(F5:F9,"FAIL")=0,"PASS","FAIL") -> PASS
A12: Interpretation | B12: Calculation integrity only; validate all gold inputs.
